getdat/__init__.py
getdat/constants.py
getdat/main.py
getdat/utils.py
getdat-0.2.2.dist-info/LICENSE.txt
getdat-0.2.2.dist-info/METADATA
getdat-0.2.2.dist-info/WHEEL
getdat-0.2.2.dist-info/entry_points.txt
getdat-0.2.2.dist-info/RECORD
