Metadata-Version: 2.1
Name: getdat
Version: 0.2.2
Summary: A command line utility for getting resources available online
Home-page: https://audiosutras.github.io/getdat/
Keywords: cli,books,movies,episodes,anna's archive,movie-web,web scraper
Author: Christopher Dixon
Author-email: chrisdixononcode@gmail.com
Requires-Python: >=3.11,<4.0
Classifier: Programming Language :: Python :: 3
Classifier: Programming Language :: Python :: 3.11
Classifier: Programming Language :: Python :: 3.12
Requires-Dist: beautifulsoup4 (>=4.12.2,<5.0.0)
Requires-Dist: click (>=8.1.7,<9.0.0)
Requires-Dist: requests (>=2.31.0,<3.0.0)
Project-URL: Repository, https://github.com/Audiosutras/getdat
